pyramid_ipython.py
pyramid_ipython-0.2.dist-info/DESCRIPTION.rst
pyramid_ipython-0.2.dist-info/METADATA
pyramid_ipython-0.2.dist-info/RECORD
pyramid_ipython-0.2.dist-info/WHEEL
pyramid_ipython-0.2.dist-info/entry_points.txt
pyramid_ipython-0.2.dist-info/metadata.json
pyramid_ipython-0.2.dist-info/top_level.txt
