Metadata-Version: 1.1
Name: pyramid-ipython
Version: 0.2
Summary: pyramid ipython pshell
Home-page: https://github.com/Pylons/pyramid_ipython
Author: Michael Merickel
Author-email: michael@merickel.org
License: BSD-derived (http://www.repoze.org/LICENSE.txt)
Platform: UNKNOWN
Classifier: Intended Audience :: Developers
Classifier: Framework :: Pyramid
Classifier: License :: Repoze Public License
Classifier: Programming Language :: Python
Classifier: Programming Language :: Python :: 2.6
Classifier: Programming Language :: Python :: 2.7
Classifier: Programming Language :: Python :: 3
Classifier: Programming Language :: Python :: 3.2
Classifier: Programming Language :: Python :: 3.3
Classifier: Programming Language :: Python :: 3.4
Classifier: Programming Language :: Python :: 3.5
Classifier: Programming Language :: Python :: Implementation :: CPython
Classifier: Programming Language :: Python :: Implementation :: PyPy
Classifier: Topic :: Internet :: WWW/HTTP
Classifier: Topic :: Internet :: WWW/HTTP :: WSGI
